dictionary/__init__.py
dictionary/dictionary.py
mokhlaroyim_raupova_very_simple_dictionary-2.0.1.dist-info/METADATA
mokhlaroyim_raupova_very_simple_dictionary-2.0.1.dist-info/WHEEL
mokhlaroyim_raupova_very_simple_dictionary-2.0.1.dist-info/top_level.txt
mokhlaroyim_raupova_very_simple_dictionary-2.0.1.dist-info/RECORD
